{"type": "FeatureCollection", "features": [{"type": "Feature", "properties": {"route_id": "ter.OCE532923", "service_id": "ter.11757", "trip_id": "ter.OCESN034677R0100126149", "trip_headsign": "34677", "trip_short_name": "34677", "direction_id": 1, "wheelchair_accessible": 0, "shape_id": "shape_048"}, "geometry": {"type": "LineString", "coordinates": [[2.0651445, 45.402313], [1.7564315, 45.25871]]}}, {"type": "Feature", "properties": {"stop_name": "Gare de Egletons", "stop_code": null, "stop_url": null, "stop_desc": null, "location_type": 0, "parent_station": "ter.StopArea_OCE87594168", "stop_id": "ter.StopPoint_OCECar_TER-87594168", "stop_timezone": null, "zone_id": null, "wheelchair_boarding": 2}, "geometry": {"type": "Point", "coordinates": [2.0651445, 45.402313]}}, {"type": "Feature", "properties": {"stop_name": "Gare de Tulle", "stop_code": null, "stop_url": null, "stop_desc": null, "location_type": 0, "parent_station": "ter.StopArea_OCE87594499", "stop_id": "ter.StopPoint_OCECar_TER-87594499", "stop_timezone": null, "zone_id": null, "wheelchair_boarding": 2}, "geometry": {"type": "Point", "coordinates": [1.7564315, 45.25871]}}]}