{"type": "FeatureCollection", "features": [{"type": "Feature", "properties": {"route_id": "ter.OCE629106", "service_id": "ter.3070", "trip_id": "ter.OCESN865875F0100264703", "trip_headsign": "865875", "trip_short_name": "865875", "direction_id": 1, "wheelchair_accessible": 0, "shape_id": "shape_339"}, "geometry": {"type": "LineString", "coordinates": [[0.9414589, 44.486397], [0.88488144, 44.443065999999995], [0.8031514, 44.37983], [0.7497826, 44.287437], [0.6759162, 44.232765], [0.62090456, 44.207972999999996]]}}, {"type": "Feature", "properties": {"stop_name": "Gare de Pont-du-Casse", "stop_code": null, "stop_url": null, "stop_desc": null, "location_type": 0, "parent_station": "ter.StopArea_OCE87586404", "stop_id": "ter.StopPoint_OCETrain_TER-87586404", "stop_timezone": null, "zone_id": null, "wheelchair_boarding": 2}, "geometry": {"type": "Point", "coordinates": [0.6759162, 44.232765]}}, {"type": "Feature", "properties": {"stop_name": "Gare de Trentels-Ladignac", "stop_code": null, "stop_url": null, "stop_desc": null, "location_type": 0, "parent_station": "ter.StopArea_OCE87586446", "stop_id": "ter.StopPoint_OCETrain_TER-87586446", "stop_timezone": null, "zone_id": null, "wheelchair_boarding": 2}, "geometry": {"type": "Point", "coordinates": [0.88488144, 44.443065999999995]}}, {"type": "Feature", "properties": {"stop_name": "Gare de Penne (Lot-et-Garonne)", "stop_code": null, "stop_url": null, "stop_desc": null, "location_type": 0, "parent_station": "ter.StopArea_OCE87586438", "stop_id": "ter.StopPoint_OCETrain_TER-87586438", "stop_timezone": null, "zone_id": null, "wheelchair_boarding": 2}, "geometry": {"type": "Point", "coordinates": [0.8031514, 44.37983]}}, {"type": "Feature", "properties": {"stop_name": "Gare de Laroque", "stop_code": null, "stop_url": null, "stop_desc": null, "location_type": 0, "parent_station": "ter.StopArea_OCE87586412", "stop_id": "ter.StopPoint_OCETrain_TER-87586412", "stop_timezone": null, "zone_id": null, "wheelchair_boarding": 2}, "geometry": {"type": "Point", "coordinates": [0.7497826, 44.287437]}}, {"type": "Feature", "properties": {"stop_name": "Gare de Agen", "stop_code": null, "stop_url": null, "stop_desc": null, "location_type": 0, "parent_station": "ter.StopArea_OCE87586008", "stop_id": "ter.StopPoint_OCETrain_TER-87586008", "stop_timezone": null, "zone_id": null, "wheelchair_boarding": 2}, "geometry": {"type": "Point", "coordinates": [0.62090456, 44.207972999999996]}}, {"type": "Feature", "properties": {"stop_name": "Gare de Monsempron-Libos", "stop_code": null, "stop_url": null, "stop_desc": null, "location_type": 0, "parent_station": "ter.StopArea_OCE87586453", "stop_id": "ter.StopPoint_OCETrain_TER-87586453", "stop_timezone": null, "zone_id": null, "wheelchair_boarding": 2}, "geometry": {"type": "Point", "coordinates": [0.9414589, 44.486397]}}]}